CHANGES.txt
CONTRIBUTORS.txt
MANIFEST.in
README.txt
setup.py
docs/HISTORY.txt
docs/INSTALL.txt
docs/LICENSE.GPL
docs/LICENSE.txt
src/ityou/__init__.py
src/ityou.esi.viewlets.egg-info/PKG-INFO
src/ityou.esi.viewlets.egg-info/SOURCES.txt
src/ityou.esi.viewlets.egg-info/dependency_links.txt
src/ityou.esi.viewlets.egg-info/entry_points.txt
src/ityou.esi.viewlets.egg-info/namespace_packages.txt
src/ityou.esi.viewlets.egg-info/not-zip-safe
src/ityou.esi.viewlets.egg-info/requires.txt
src/ityou.esi.viewlets.egg-info/top_level.txt
src/ityou/esi/__init__.py
src/ityou/esi/viewlets/__init__.py
src/ityou/esi/viewlets/configure.zcml
src/ityou/esi/viewlets/interfaces.py
src/ityou/esi/viewlets/testing.py
src/ityou/esi/viewlets/testing.zcml
src/ityou/esi/viewlets/translate.sh
src/ityou/esi/viewlets/viewlets.py
src/ityou/esi/viewlets/images/document-big.png
src/ityou/esi/viewlets/images/event-big.png
src/ityou/esi/viewlets/images/file-big.png
src/ityou/esi/viewlets/images/folder-big.png
src/ityou/esi/viewlets/images/image-big.png
src/ityou/esi/viewlets/images/link-big.png
src/ityou/esi/viewlets/images/news-big.png
src/ityou/esi/viewlets/images/no-picture-big.png
src/ityou/esi/viewlets/images/topic-big.png
src/ityou/esi/viewlets/javascripts/esi-livesearch.js
src/ityou/esi/viewlets/javascripts/esi-new-content.js
src/ityou/esi/viewlets/locales/ityou.esi.viewlets.pot
src/ityou/esi/viewlets/locales/de/LC_MESSAGES/ityou.esi.viewlets.po
src/ityou/esi/viewlets/locales/en/LC_MESSAGES/ityou.esi.viewlets.po
src/ityou/esi/viewlets/profiles/default/browserlayer.xml
src/ityou/esi/viewlets/profiles/default/cssregistry.xml
src/ityou/esi/viewlets/profiles/default/jsregistry.xml
src/ityou/esi/viewlets/profiles/default/metadata.xml
src/ityou/esi/viewlets/profiles/default/viewlets.xml
src/ityou/esi/viewlets/profiles/testing/metadata.xml
src/ityou/esi/viewlets/stylesheets/livesearch.css
src/ityou/esi/viewlets/stylesheets/new-content.css
src/ityou/esi/viewlets/templates/livesearch.pt
src/ityou/esi/viewlets/templates/livesearch_contents.html
src/ityou/esi/viewlets/templates/livesearch_users.html
src/ityou/esi/viewlets/templates/new_content.pt
src/ityou/esi/viewlets/tests/__init__.py
src/ityou/esi/viewlets/tests/test_setup.py