Metadata-Version: 1.1
Name: ityou.esi.viewlets
Version: 1.3.1
Summary: ITYOU ESI viewlets
Home-page: http://www.ityou.de/esi/
Author: ITYOU/LM
Author-email: lm@ityou.de
License: GPL
Keywords: Social Intranet,Plone,viewlets
Platform: UNKNOWN
Classifier: Framework :: Plone
Classifier: Programming Language :: Python
